{
    "version": 1,
    "stopwords": [
        "le",
        "la",
        "les",
        "un",
        "une",
        "des",
        "du",
        "au",
        "aux",
        "ce",
        "cet",
        "cette",
        "ces",
        "mon",
        "ma",
        "mes",
        "ton",
        "ta",
        "tes",
        "son",
        "sa",
        "ses",
        "notre",
        "nos",
        "votre",
        "vos",
        "leur",
        "leurs",
        "chaque",
        "quelques",
        "plusieurs",
        "tout",
        "tous",
        "toute",
        "toutes",
        "autre",
        "autres",
        "même",
        "mêmes",
        "je",
        "tu",
        "il",
        "elle",
        "on",
        "nous",
        "vous",
        "ils",
        "elles",
        "me",
        "te",
        "se",
        "moi",
        "toi",
        "lui",
        "eux",
        "en",
        "y",
        "qui",
        "que",
        "quoi",
        "dont",
        "où",
        "cela",
        "ceci",
        "ça",
        "celui",
        "celle",
        "ceux",
        "celles",
        "rien",
        "personne",
        "et",
        "ou",
        "mais",
        "donc",
        "or",
        "ni",
        "car",
        "si",
        "ne",
        "pas",
        "plus",
        "moins",
        "très",
        "aussi",
        "comme",
        "quand",
        "alors",
        "puis",
        "ici",
        "là",
        "à",
        "de",
        "dans",
        "sur",
        "sous",
        "avec",
        "sans",
        "pour",
        "par",
        "entre",
        "vers",
        "chez",
        "avant",
        "après",
        "depuis",
        "pendant",
        "contre",
        "selon",
        "être",
        "suis",
        "es",
        "est",
        "sommes",
        "êtes",
        "sont",
        "étais",
        "était",
        "étaient",
        "fut",
        "furent",
        "été",
        "sera",
        "serait",
        "avoir",
        "ai",
        "as",
        "a",
        "avons",
        "avez",
        "ont",
        "avais",
        "avait",
        "avaient",
        "eut",
        "eu",
        "aura",
        "aurait",
        "c'est",
        "c'était",
        "n'est",
        "n'était",
        "n'a",
        "n'avait",
        "d'un",
        "d'une",
        "j'ai",
        "j'avais",
        "l'on",
        "qu'il",
        "qu'ils",
        "qu'elle",
        "qu'on",
        "qu'un",
        "jusqu'à",
        "aujourd'hui",
        "quelqu'un",
        "s'est",
        "s'il",
        "c’est",
        "c’était",
        "n’est",
        "n’était",
        "n’a",
        "n’avait",
        "d’un",
        "d’une",
        "j’ai",
        "j’avais",
        "l’on",
        "qu’il",
        "qu’ils",
        "qu’elle",
        "qu’on",
        "qu’un",
        "jusqu’à",
        "aujourd’hui",
        "quelqu’un",
        "s’est",
        "s’il"
    ],
    "fillers": [
        "vraiment",
        "simplement",
        "effectivement",
        "finalement",
        "plutôt",
        "carrément",
        "franchement",
        "soudain",
        "soudainement",
        "brusquement",
        "subitement",
        "absolument",
        "complètement",
        "totalement",
        "parfaitement",
        "littéralement",
        "apparemment",
        "visiblement",
        "manifestement",
        "évidemment",
        "naturellement",
        "certainement",
        "probablement",
        "sûrement",
        "assurément",
        "décidément",
        "réellement",
        "véritablement",
        "quasiment",
        "pratiquement",
        "presque",
        "juste",
        "enfin",
        "bref",
        "justement",
        "précisément",
        "notamment",
        "tellement",
        "extrêmement",
        "terriblement",
        "incroyablement",
        "particulièrement",
        "immédiatement",
        "aussitôt"
    ],
    "weakVerbs": [
        "faire",
        "fais",
        "fait",
        "faites",
        "font",
        "faisait",
        "faisaient",
        "faisant",
        "fit",
        "firent",
        "fera",
        "feront",
        "ferait",
        "feraient",
        "alla",
        "allait",
        "allaient",
        "allèrent",
        "mit",
        "mirent",
        "mettait",
        "mettaient"
    ],
    "filterWords": [
        "vit",
        "voit",
        "voyait",
        "voyaient",
        "virent",
        "aperçut",
        "apercevait",
        "aperçurent",
        "regarda",
        "regardait",
        "regardèrent",
        "entendit",
        "entendait",
        "entendirent",
        "entend",
        "écouta",
        "écoutait",
        "sentit",
        "sentait",
        "sentirent",
        "ressentit",
        "ressentait",
        "pensa",
        "pensait",
        "pensèrent",
        "pense",
        "songea",
        "songeait",
        "crut",
        "croyait",
        "crurent",
        "croit",
        "savait",
        "savaient",
        "sut",
        "comprit",
        "comprenait",
        "comprirent",
        "sembla",
        "semblait",
        "semblaient",
        "semble",
        "parut",
        "paraissait",
        "paraissaient",
        "paraît",
        "remarqua",
        "remarquait",
        "remarquèrent",
        "observa",
        "observait",
        "constata",
        "constatait",
        "devina",
        "devinait",
        "réalisa",
        "réalisait",
        "imagina",
        "imaginait",
        "éprouva",
        "éprouvait",
        "perçut",
        "percevait",
        "souvint",
        "souvenait"
    ],
    "cliches": [
        "commença à",
        "commençait à",
        "commencèrent à",
        "se mit à",
        "se mirent à",
        "se mettait à",
        "tout à coup",
        "tout d'un coup",
        "tout d’un coup",
        "sain et sauf",
        "saine et sauve",
        "au fur et à mesure",
        "sans crier gare",
        "à pas de loup",
        "un silence de mort",
        "blanc comme un linge",
        "blanche comme un linge",
        "rouge comme une tomate",
        "le calme avant la tempête",
        "une peur bleue",
        "froid dans le dos",
        "en train de",
        "avait l'air",
        "avait l’air",
        "se rendit compte",
        "se rendait compte",
        "pour ainsi dire",
        "en quelque sorte",
        "à vrai dire",
        "de toute évidence",
        "en fin de compte",
        "au bout du compte",
        "la cerise sur le gâteau",
        "au grand jamais",
        "un froid de canard",
        "pleuvait des cordes",
        "poussa un soupir de soulagement",
        "le cœur battant la chamade"
    ],
    "patterns": [
        {
            "id": "passive",
            "regex": "(?<![\\p{L}\\p{M}])(?:est|était|étaient|fut|furent|sont|sera|seront|serait|seraient)\\s+(?:pas\\s+)?\\p{L}+ée?s?(?![\\p{L}\\p{M}])"
        },
        {
            "id": "ilYA",
            "regex": "(?<![\\p{L}\\p{M}])il\\s+(?:n['’])?y\\s+(?:avait|aurait|aura|eut|a)(?![\\p{L}\\p{M}])"
        }
    ],
    "adjectiveSuffixes": [
        "eux",
        "euse",
        "euses",
        "ique",
        "iques",
        "able",
        "ables",
        "ible",
        "ibles",
        "if",
        "ifs",
        "ive",
        "ives"
    ],
    "readability": { "formula": "kandel" }
}
